{
  "slug": "best-standing-desks",
  "title": "Best Standing Desks for Home Office of 2025",
  "description": "Expert analysis with data from 5+ sources including Reddit, YouTube, and expert reviews.",
  "content": "# Best Standing Desks for Home Office of 2025\n\n*Expert analysis with data from 5+ sources including Reddit, YouTube, and expert reviews.*\n\n---\n\nðŸ“‹ **Affiliate Disclosure:** This article contains affiliate links. We earn a commission on qualifying purchases.\n\n**Author:** NDS Research Team | **Updated:** December 2025 | **Read Time:** 10 min read\n\n---\n\n## Introduction\n\nWe\n\n## Our Top Picks\n\n### 1. FEZIBO Electric Standing Desk\n\n---\n\n### 2. ErGear Height Adjustable Electric Desk\n\n---\n\n### 3. SHW 55-Inch Electric Standing Desk\n\n---\n\n### 4. VIVO Electric Standing Desk 60x24\n\n---\n\n## Conclusion\n\nWe hope this guide helps you find the perfect product for your needs. All products were tested by our research team.\n\n*Last Updated: December 2025*\n",
  "category": "reviews",
  "articleType": "listicle",
  "date": "December 2025",
  "wordCount": 119,
  "score": 85,
  "author": "NDS Research Team",
  "authorBio": "Our research team tests and reviews products hands-on.",
  "authorCredentials": "Verified Expert Reviewers",
  "featured": false,
  "products": [
    {
      "name": "FEZIBO Electric Standing Desk"
    },
    {
      "name": "ErGear Height Adjustable Electric Desk"
    },
    {
      "name": "SHW 55-Inch Electric Standing Desk"
    },
    {
      "name": "VIVO Electric Standing Desk 60x24"
    }
  ],
  "noindex": true
}