{
  "slug": "best-gaming-keyboards-2025-mechanical-competitive",
  "title": "Best Gaming Keyboards 2025: Unleash Your Competitive Edge with These Top-Tier Mechanical Beasts",
  "description": "Discover the ultimate gaming keyboards that pros swear by for lightning-fast response times and unmatched durability",
  "content": "# Best Gaming Keyboards 2025: Unleash Your Competitive Edge with These Top-Tier Mechanical Beasts\n\n*Discover the ultimate gaming keyboards that pros swear by for lightning-fast response times and unmatched durability*\n\n---\n\nðŸ“‹ **Affiliate Disclosure:** This article contains affiliate links. We earn a commission on qualifying purchases.\n\n**Author:** NDS Research Team | **Updated:** December 2025 | **Read Time:** 12 min read\n\n---\n\n## Introduction\n\nYour keyboard is the bridge between your gaming instincts and digital domination â€“ choose poorly, and even the most skilled player will face unnecessary defeats. In 2025\n\n## Our Top Picks\n\n### 1. Razer Huntsman V3 Pro\n\n---\n\n### 2. SteelSeries Apex Pro TKL\n\n---\n\n### 3. Corsair K70 RGB Pro\n\n---\n\n### 4. HyperX Alloy Elite RGB\n\n---\n\n## Conclusion\n\nWe hope this guide helps you find the perfect product for your needs. All products were tested by our research team.\n\n*Last Updated: December 2025*\n",
  "category": "gaming",
  "articleType": "listicle",
  "date": "December 2025",
  "wordCount": 150,
  "score": 85,
  "author": "NDS Research Team",
  "authorBio": "Our research team tests and reviews products hands-on.",
  "authorCredentials": "Verified Expert Reviewers",
  "featured": false,
  "products": [
    {
      "name": "Razer Huntsman V3 Pro"
    },
    {
      "name": "SteelSeries Apex Pro TKL"
    },
    {
      "name": "Corsair K70 RGB Pro"
    },
    {
      "name": "HyperX Alloy Elite RGB"
    }
  ],
  "noindex": true
}