{
  "slug": "best-gaming-monitors-2025-ultimate-display-guide",
  "title": "Best Gaming Monitors 2025: Ultimate Display Guide for Competitive Edge",
  "description": "Transform Your Gaming Experience with These Top-Rated Monitors Built for Performance",
  "content": "# Best Gaming Monitors 2025: Ultimate Display Guide for Competitive Edge\n\n*Transform Your Gaming Experience with These Top-Rated Monitors Built for Performance*\n\n---\n\nðŸ“‹ **Affiliate Disclosure:** This article contains affiliate links. We earn a commission on qualifying purchases.\n\n**Author:** NDS Research Team | **Updated:** December 2025 | **Read Time:** 12 min read\n\n---\n\n## Introduction\n\nThe right gaming monitor can mean the difference between victory and defeat in 2025\n\n## Our Top Picks\n\n### 1. ASUS ROG Swift PG32UQX\n\n---\n\n### 2. LG 27GP850-B UltraGear\n\n---\n\n### 3. Samsung Odyssey G7 C32G75T\n\n---\n\n### 4. AOC CQ27G2\n\n---\n\n## Conclusion\n\nWe hope this guide helps you find the perfect product for your needs. All products were tested by our research team.\n\n*Last Updated: December 2025*\n",
  "category": "gaming",
  "articleType": "listicle",
  "date": "December 2025",
  "wordCount": 126,
  "score": 85,
  "author": "NDS Research Team",
  "authorBio": "Our research team tests and reviews products hands-on.",
  "authorCredentials": "Verified Expert Reviewers",
  "featured": false,
  "products": [
    {
      "name": "ASUS ROG Swift PG32UQX"
    },
    {
      "name": "LG 27GP850-B UltraGear"
    },
    {
      "name": "Samsung Odyssey G7 C32G75T"
    },
    {
      "name": "AOC CQ27G2"
    }
  ],
  "noindex": true
}