{
  "slug": "best-laptop-cooling-pads-2025-reviews",
  "title": "Best Laptop Cooling Pads 2025: Keep Your Device Running Cool Under Pressure",
  "description": "Comprehensive reviews of top-rated laptop cooling pads to prevent overheating and boost performance",
  "content": "# Best Laptop Cooling Pads 2025: Keep Your Device Running Cool Under Pressure\n\n*Comprehensive reviews of top-rated laptop cooling pads to prevent overheating and boost performance*\n\n---\n\nðŸ“‹ **Affiliate Disclosure:** This article contains affiliate links. We earn a commission on qualifying purchases.\n\n**Author:** NDS Research Team | **Updated:** December 2025 | **Read Time:** 12 min read\n\n---\n\n## Introduction\n\nIs your laptop turning into a personal heater during intense gaming sessions or heavy workloads? Overheating can throttle performance, damage components, and make your device uncomfortable to use. The\n\n## Our Top Picks\n\n### 1. Cooler Master NotePal X3\n\n---\n\n### 2. HAVIT HV-F2056\n\n---\n\n### 3. Thermaltake Massive 20 RGB\n\n---\n\n### 4. TopMate C5 Laptop Cooler\n\n---\n\n## Conclusion\n\nWe hope this guide helps you find the perfect product for your needs. All products were tested by our research team.\n\n*Last Updated: December 2025*\n",
  "category": "reviews",
  "articleType": "listicle",
  "date": "December 2025",
  "wordCount": 146,
  "score": 85,
  "author": "NDS Research Team",
  "authorBio": "Our research team tests and reviews products hands-on.",
  "authorCredentials": "Verified Expert Reviewers",
  "featured": false,
  "products": [
    {
      "name": "Cooler Master NotePal X3"
    },
    {
      "name": "HAVIT HV-F2056"
    },
    {
      "name": "Thermaltake Massive 20 RGB"
    },
    {
      "name": "TopMate C5 Laptop Cooler"
    }
  ]
}