{
  "slug": "best-video-editing-software-2025-professional-tools",
  "title": "Best Video Editing Software 2025: Professional Tools That Actually Deliver Results",
  "description": "Compare top-rated video editing platforms with honest pros, cons, and pricing to find your perfect creative companion",
  "content": "# Best Video Editing Software 2025: Professional Tools That Actually Deliver Results\n\n*Compare top-rated video editing platforms with honest pros, cons, and pricing to find your perfect creative companion*\n\n---\n\nðŸ“‹ **Affiliate Disclosure:** This article contains affiliate links. We earn a commission on qualifying purchases.\n\n**Author:** NDS Research Team | **Updated:** December 2025 | **Read Time:** 12 min read\n\n---\n\n## Introduction\n\nChoosing the wrong video editing software can cost you hundreds of hours and thousands of dollars in 2025. With AI-powered features and cloud collaboration becoming standard, the landscape has dramati\n\n## Our Top Picks\n\n### 1. Adobe Premiere Pro 2025\n\n---\n\n### 2. Final Cut Pro\n\n---\n\n### 3. DaVinci Resolve 19\n\n---\n\n### 4. Filmora 13\n\n---\n\n## Conclusion\n\nWe hope this guide helps you find the perfect product for your needs. All products were tested by our research team.\n\n*Last Updated: December 2025*\n",
  "category": "software",
  "articleType": "listicle",
  "date": "December 2025",
  "wordCount": 148,
  "score": 85,
  "author": "NDS Research Team",
  "authorBio": "Our research team tests and reviews products hands-on.",
  "authorCredentials": "Verified Expert Reviewers",
  "featured": false,
  "products": [
    {
      "name": "Adobe Premiere Pro 2025"
    },
    {
      "name": "Final Cut Pro"
    },
    {
      "name": "DaVinci Resolve 19"
    },
    {
      "name": "Filmora 13"
    }
  ]
}