{
  "slug": "best-gaming-mice-2025-precision-competitive",
  "title": "Best Gaming Mice 2025: Ultimate Precision Weapons for Competitive Gamers",
  "description": "Discover the top gaming mice that deliver lightning-fast response times, ergonomic comfort, and customizable features for every gaming style",
  "content": "# Best Gaming Mice 2025: Ultimate Precision Weapons for Competitive Gamers\n\n*Discover the top gaming mice that deliver lightning-fast response times, ergonomic comfort, and customizable features for every gaming style*\n\n---\n\nðŸ“‹ **Affiliate Disclosure:** This article contains affiliate links. We earn a commission on qualifying purchases.\n\n**Author:** NDS Research Team | **Updated:** December 2025 | **Read Time:** 12 min read\n\n---\n\n## Introduction\n\nYour gaming performance is only as good as your weakest link, and for many players, that\n\n## Our Top Picks\n\n### 1. Logitech G Pro X Superlight 2\n\n---\n\n### 2. Razer DeathAdder V4 Pro\n\n---\n\n### 3. SteelSeries Rival 650 Wireless\n\n---\n\n### 4. Corsair M65 RGB Elite\n\n---\n\n## Conclusion\n\nWe hope this guide helps you find the perfect product for your needs. All products were tested by our research team.\n\n*Last Updated: December 2025*\n",
  "category": "gaming",
  "articleType": "listicle",
  "date": "December 2025",
  "wordCount": 141,
  "score": 85,
  "author": "NDS Research Team",
  "authorBio": "Our research team tests and reviews products hands-on.",
  "authorCredentials": "Verified Expert Reviewers",
  "featured": false,
  "products": [
    {
      "name": "Logitech G Pro X Superlight 2"
    },
    {
      "name": "Razer DeathAdder V4 Pro"
    },
    {
      "name": "SteelSeries Rival 650 Wireless"
    },
    {
      "name": "Corsair M65 RGB Elite"
    }
  ]
}